pydont/__init__.py
pydont/example.py
pydont-1.0.1.dist-info/METADATA
pydont-1.0.1.dist-info/WHEEL
pydont-1.0.1.dist-info/RECORD
